README
setup.py
django_gems/__init__.py
django_gems/jqgrid.py
django_gems/json.py
django_gems/xls.py
django_gems.egg-info/PKG-INFO
django_gems.egg-info/SOURCES.txt
django_gems.egg-info/dependency_links.txt
django_gems.egg-info/top_level.txt
django_gems/db/__init__.py
django_gems/db/models/__init__.py
django_gems/db/models/fields.py
django_gems/db/models/query.py
django_gems/templatetags/__init__.py
django_gems/templatetags/analytics.py
django_gems/templatetags/base64.py
django_gems/templatetags/currency.py
django_gems/templatetags/qr.py
django_gems/templatetags/raw.py
django_gems/templatetags/safewrap.py
django_gems/utils/__init__.py
django_gems/utils/log.py